{
  "playerPuntingStatInfoList": [
    {
      "fullName": "R.Rehkow",
      "puntsBlocked": 0,
      "puntsIn20": 0,
      "puntLongest": 64,
      "puntTBs": 2,
      "puntNetYdsPerAtt": 57.3333,
      "puntNetYds": 172,
      "puntAtt": 3,
      "puntYdsPerAtt": 57.3333,
      "puntYds": 172,
      "rosterId": 553388192,
      "scheduleId": 544735502,
      "seasonIndex": 3,
      "statId": 547619362,
      "stageIndex": 1,
      "teamId": 775553058,
      "weekIndex": 0
    },
    {
      "fullName": "Z.Harris",
      "puntsBlocked": 0,
      "puntsIn20": 0,
      "puntLongest": 68,
      "puntTBs": 2,
      "puntNetYdsPerAtt": 58.3333,
      "puntNetYds": 175,
      "puntAtt": 3,
      "puntYdsPerAtt": 58.3333,
      "puntYds": 175,
      "rosterId": 553386605,
      "scheduleId": 544735502,
      "seasonIndex": 3,
      "statId": 547619819,
      "stageIndex": 1,
      "teamId": 775553047,
      "weekIndex": 0
    },
    {
      "fullName": "T.Taylor",
      "puntsBlocked": 0,
      "puntsIn20": 0,
      "puntLongest": 64,
      "puntTBs": 1,
      "puntNetYdsPerAtt": 64.0,
      "puntNetYds": 64,
      "puntAtt": 1,
      "puntYdsPerAtt": 64.0,
      "puntYds": 64,
      "rosterId": 553388585,
      "scheduleId": 544735504,
      "seasonIndex": 3,
      "statId": 547618864,
      "stageIndex": 1,
      "teamId": 775553049,
      "weekIndex": 0
    },
    {
      "fullName": "C.Urban",
      "puntsBlocked": 0,
      "puntsIn20": 0,
      "puntLongest": 41,
      "puntTBs": 0,
      "puntNetYdsPerAtt": 35.0,
      "puntNetYds": 70,
      "puntAtt": 2,
      "puntYdsPerAtt": 40.0,
      "puntYds": 80,
      "rosterId": 553388391,
      "scheduleId": 544735510,
      "seasonIndex": 3,
      "statId": 547619293,
      "stageIndex": 1,
      "teamId": 775553060,
      "weekIndex": 0
    },
    {
      "fullName": "D.Whelan",
      "puntsBlocked": 0,
      "puntsIn20": 2,
      "puntLongest": 60,
      "puntTBs": 0,
      "puntNetYdsPerAtt": 41.6667,
      "puntNetYds": 125,
      "puntAtt": 3,
      "puntYdsPerAtt": 44.0,
      "puntYds": 132,
      "rosterId": 553388845,
      "scheduleId": 544735512,
      "seasonIndex": 3,
      "statId": 547618975,
      "stageIndex": 1,
      "teamId": 775553027,
      "weekIndex": 0
    },
    {
      "fullName": "E.Gentry",
      "puntsBlocked": 0,
      "puntsIn20": 2,
      "puntLongest": 63,
      "puntTBs": 0,
      "puntNetYdsPerAtt": 44.75,
      "puntNetYds": 179,
      "puntAtt": 4,
      "puntYdsPerAtt": 48.0,
      "puntYds": 192,
      "rosterId": 553388691,
      "scheduleId": 544735512,
      "seasonIndex": 3,
      "statId": 547619119,
      "stageIndex": 1,
      "teamId": 775553054,
      "weekIndex": 0
    },
    {
      "fullName": "J.Stout",
      "puntsBlocked": 0,
      "puntsIn20": 1,
      "puntLongest": 66,
      "puntTBs": 0,
      "puntNetYdsPerAtt": 66.0,
      "puntNetYds": 66,
      "puntAtt": 1,
      "puntYdsPerAtt": 66.0,
      "puntYds": 66,
      "rosterId": 553388524,
      "scheduleId": 544735516,
      "seasonIndex": 3,
      "statId": 547618977,
      "stageIndex": 1,
      "teamId": 775553059,
      "weekIndex": 0
    },
    {
      "fullName": "A.Watkins",
      "puntsBlocked": 0,
      "puntsIn20": 0,
      "puntLongest": 59,
      "puntTBs": 1,
      "puntNetYdsPerAtt": 51.5,
      "puntNetYds": 103,
      "puntAtt": 2,
      "puntYdsPerAtt": 54.5,
      "puntYds": 109,
      "rosterId": 553386426,
      "scheduleId": 544735516,
      "seasonIndex": 3,
      "statId": 547619335,
      "stageIndex": 1,
      "teamId": 775553036,
      "weekIndex": 0
    },
    {
      "fullName": "J.Fox",
      "puntsBlocked": 0,
      "puntsIn20": 1,
      "puntLongest": 55,
      "puntTBs": 1,
      "puntNetYdsPerAtt": 47.75,
      "puntNetYds": 191,
      "puntAtt": 4,
      "puntYdsPerAtt": 48.75,
      "puntYds": 195,
      "rosterId": 553386841,
      "scheduleId": 544735524,
      "seasonIndex": 3,
      "statId": 547619923,
      "stageIndex": 1,
      "teamId": 775553030,
      "weekIndex": 0
    },
    {
      "fullName": "K.Kroeger",
      "puntsBlocked": 0,
      "puntsIn20": 1,
      "puntLongest": 58,
      "puntTBs": 0,
      "puntNetYdsPerAtt": 43.5,
      "puntNetYds": 87,
      "puntAtt": 2,
      "puntYdsPerAtt": 49.5,
      "puntYds": 99,
      "rosterId": 553389200,
      "scheduleId": 544735524,
      "seasonIndex": 3,
      "statId": 547618908,
      "stageIndex": 1,
      "teamId": 775553050,
      "weekIndex": 0
    },
    {
      "fullName": "M.Wishnowsky",
      "puntsBlocked": 0,
      "puntsIn20": 0,
      "puntLongest": 54,
      "puntTBs": 1,
      "puntNetYdsPerAtt": 48.5,
      "puntNetYds": 97,
      "puntAtt": 2,
      "puntYdsPerAtt": 52.0,
      "puntYds": 104,
      "rosterId": 553388948,
      "scheduleId": 544735529,
      "seasonIndex": 3,
      "statId": 547619771,
      "stageIndex": 1,
      "teamId": 775553046,
      "weekIndex": 0
    },
    {
      "fullName": "B.Baringer",
      "puntsBlocked": 0,
      "puntsIn20": 1,
      "puntLongest": 50,
      "puntTBs": 0,
      "puntNetYdsPerAtt": 50.0,
      "puntNetYds": 50,
      "puntAtt": 1,
      "puntYdsPerAtt": 50.0,
      "puntYds": 50,
      "rosterId": 553386124,
      "scheduleId": 544735529,
      "seasonIndex": 3,
      "statId": 547619570,
      "stageIndex": 1,
      "teamId": 775553051,
      "weekIndex": 0
    },
    {
      "fullName": "D.Winters",
      "puntsBlocked": 0,
      "puntsIn20": 0,
      "puntLongest": 42,
      "puntTBs": 0,
      "puntNetYdsPerAtt": 39.0,
      "puntNetYds": 117,
      "puntAtt": 3,
      "puntYdsPerAtt": 41.0,
      "puntYds": 123,
      "rosterId": 553388700,
      "scheduleId": 544735530,
      "seasonIndex": 3,
      "statId": 547619124,
      "stageIndex": 1,
      "teamId": 775553026,
      "weekIndex": 0
    },
    {
      "fullName": "M.Araiza",
      "puntsBlocked": 0,
      "puntsIn20": 0,
      "puntLongest": 69,
      "puntTBs": 1,
      "puntNetYdsPerAtt": 49.0,
      "puntNetYds": 49,
      "puntAtt": 1,
      "puntYdsPerAtt": 69.0,
      "puntYds": 69,
      "rosterId": 553386072,
      "scheduleId": 544735530,
      "seasonIndex": 3,
      "statId": 547619653,
      "stageIndex": 1,
      "teamId": 775553029,
      "weekIndex": 0
    },
    {
      "fullName": "C.Bojorquez",
      "puntsBlocked": 0,
      "puntsIn20": 0,
      "puntLongest": 43,
      "puntTBs": 0,
      "puntNetYdsPerAtt": 34.0,
      "puntNetYds": 68,
      "puntAtt": 2,
      "puntYdsPerAtt": 41.0,
      "puntYds": 82,
      "rosterId": 553386223,
      "scheduleId": 544735498,
      "seasonIndex": 3,
      "statId": 547619409,
      "stageIndex": 1,
      "teamId": 775553025,
      "weekIndex": 0
    },
    {
      "fullName": "B.Robbins",
      "puntsBlocked": 0,
      "puntsIn20": 0,
      "puntLongest": 59,
      "puntTBs": 1,
      "puntNetYdsPerAtt": 46.0,
      "puntNetYds": 92,
      "puntAtt": 2,
      "puntYdsPerAtt": 49.5,
      "puntYds": 99,
      "rosterId": 553388234,
      "scheduleId": 544735507,
      "seasonIndex": 3,
      "statId": 547619661,
      "stageIndex": 1,
      "teamId": 775553024,
      "weekIndex": 0
    },
    {
      "fullName": "R.Sanchez",
      "puntsBlocked": 0,
      "puntsIn20": 0,
      "puntLongest": 52,
      "puntTBs": 0,
      "puntNetYdsPerAtt": 43.5,
      "puntNetYds": 87,
      "puntAtt": 2,
      "puntYdsPerAtt": 48.0,
      "puntYds": 96,
      "rosterId": 553388317,
      "scheduleId": 544735507,
      "seasonIndex": 3,
      "statId": 547619298,
      "stageIndex": 1,
      "teamId": 775553031,
      "weekIndex": 0
    },
    {
      "fullName": "A.Cole",
      "puntsBlocked": 0,
      "puntsIn20": 0,
      "puntLongest": 69,
      "puntTBs": 1,
      "puntNetYdsPerAtt": 55.75,
      "puntNetYds": 223,
      "puntAtt": 4,
      "puntYdsPerAtt": 63.5,
      "puntYds": 254,
      "rosterId": 553386479,
      "scheduleId": 544735488,
      "seasonIndex": 3,
      "statId": 547618890,
      "stageIndex": 1,
      "teamId": 775553052,
      "weekIndex": 0
    },
    {
      "fullName": "M.Dickson",
      "puntsBlocked": 0,
      "puntsIn20": 1,
      "puntLongest": 70,
      "puntTBs": 1,
      "puntNetYdsPerAtt": 55.3333,
      "puntNetYds": 166,
      "puntAtt": 3,
      "puntYdsPerAtt": 60.0,
      "puntYds": 180,
      "rosterId": 553386638,
      "scheduleId": 544735517,
      "seasonIndex": 3,
      "statId": 547618943,
      "stageIndex": 1,
      "teamId": 775553056,
      "weekIndex": 0
    },
    {
      "fullName": "B.Pinion",
      "puntsBlocked": 0,
      "puntsIn20": 1,
      "puntLongest": 63,
      "puntTBs": 1,
      "puntNetYdsPerAtt": 49.4,
      "puntNetYds": 247,
      "puntAtt": 5,
      "puntYdsPerAtt": 54.4,
      "puntYds": 272,
      "rosterId": 553388105,
      "scheduleId": 544735517,
      "seasonIndex": 3,
      "statId": 547619054,
      "stageIndex": 1,
      "teamId": 775553053,
      "weekIndex": 0
    },
    {
      "fullName": "E.Evans",
      "puntsBlocked": 0,
      "puntsIn20": 1,
      "puntLongest": 48,
      "puntTBs": 0,
      "puntNetYdsPerAtt": 35.6667,
      "puntNetYds": 107,
      "puntAtt": 3,
      "puntYdsPerAtt": 40.6667,
      "puntYds": 122,
      "rosterId": 553386755,
      "scheduleId": 544735509,
      "seasonIndex": 3,
      "statId": 547619326,
      "stageIndex": 1,
      "teamId": 775553057,
      "weekIndex": 0
    },
    {
      "fullName": "E.Walton",
      "puntsBlocked": 0,
      "puntsIn20": 0,
      "puntLongest": 47,
      "puntTBs": 0,
      "puntNetYdsPerAtt": 36.5,
      "puntNetYds": 146,
      "puntAtt": 4,
      "puntYdsPerAtt": 46.0,
      "puntYds": 184,
      "rosterId": 553388080,
      "scheduleId": 544735509,
      "seasonIndex": 3,
      "statId": 547619146,
      "stageIndex": 1,
      "teamId": 775553043,
      "weekIndex": 0
    },
    {
      "fullName": "J.Summers",
      "puntsBlocked": 0,
      "puntsIn20": 0,
      "puntLongest": 65,
      "puntTBs": 0,
      "puntNetYdsPerAtt": 51.0,
      "puntNetYds": 102,
      "puntAtt": 2,
      "puntYdsPerAtt": 60.0,
      "puntYds": 120,
      "rosterId": 553387900,
      "scheduleId": 544735508,
      "seasonIndex": 3,
      "statId": 547618914,
      "stageIndex": 1,
      "teamId": 775553040,
      "weekIndex": 0
    },
    {
      "fullName": "R.Wright",
      "puntsBlocked": 0,
      "puntsIn20": 1,
      "puntLongest": 67,
      "puntTBs": 0,
      "puntNetYdsPerAtt": 44.3333,
      "puntNetYds": 133,
      "puntAtt": 3,
      "puntYdsPerAtt": 48.0,
      "puntYds": 144,
      "rosterId": 553388991,
      "scheduleId": 544735508,
      "seasonIndex": 3,
      "statId": 547619782,
      "stageIndex": 1,
      "teamId": 775553037,
      "weekIndex": 0
    },
    {
      "fullName": "J.Crawshaw",
      "puntsBlocked": 0,
      "puntsIn20": 1,
      "puntLongest": 66,
      "puntTBs": 2,
      "puntNetYdsPerAtt": 56.3333,
      "puntNetYds": 169,
      "puntAtt": 3,
      "puntYdsPerAtt": 56.3333,
      "puntYds": 169,
      "rosterId": 553386533,
      "scheduleId": 544735514,
      "seasonIndex": 3,
      "statId": 547619282,
      "stageIndex": 1,
      "teamId": 775553028,
      "weekIndex": 0
    },
    {
      "fullName": "A.McNamara",
      "puntsBlocked": 0,
      "puntsIn20": 0,
      "puntLongest": 42,
      "puntTBs": 1,
      "puntNetYdsPerAtt": 22.0,
      "puntNetYds": 22,
      "puntAtt": 1,
      "puntYdsPerAtt": 42.0,
      "puntYds": 42,
      "rosterId": 553387763,
      "scheduleId": 544735489,
      "seasonIndex": 3,
      "statId": 547619525,
      "stageIndex": 1,
      "teamId": 775553035,
      "weekIndex": 0
    }
  ],
  "message": "",
  "success": true
}